pyvk/__init__.py
pyvk/api.py
pyvk/auth.py
pyvk/config.py
pyvk/constants.py
pyvk/exceptions.py
pyvk/utils.py
pyvk/helpers/__init__.py
pyvk/helpers/uploaders.py
pyvk/helpers/reqn/__init__.py
pyvk/helpers/reqn/reqn.py
pyvk/helpers/reqn/results.py
pyvk-0.2.3.dist-info/METADATA
pyvk-0.2.3.dist-info/WHEEL
pyvk-0.2.3.dist-info/licenses/LICENSE
pyvk-0.2.3.dist-info/RECORD
