Metadata-Version: 2.3
Name: pyvk
Version: 0.2.3
Summary: VK API for Python
Project-URL: Documentation, https://pyvk.mkuznets.com
Project-URL: GitHub, https://github.com/mkuznets/pyvk
Author-email: Max Kuznetsov <maks.kuznetsov@gmail.com>
License: MIT
License-File: LICENSE
Requires-Python: >=3.8
Requires-Dist: appdirs
Requires-Dist: lxml
Requires-Dist: requests
